commensurability-1.1.1.dist-info/METADATA
commensurability-1.1.1.dist-info/WHEEL
commensurability-1.1.1.dist-info/entry_points.txt
commensurability-1.1.1.dist-info/licenses/LICENSE
commensurability/__init__.py
commensurability/analysis.py
commensurability/evaluation.py
commensurability/tessellation/__init__.py
commensurability/tessellation/base.py
commensurability/tessellation/constructor.py
commensurability/tessellation/dim2.py
commensurability/tessellation/dim3.py
commensurability/tessellation/exceptions.py
commensurability/tessellation/generic.py
commensurability/utils.py
commensurability/viewer.py
commensurability-1.1.1.dist-info/RECORD
