Metadata-Version: 2.1
Name: commensurability
Version: 1.1.1
Summary: A package for analyzing orbit commensurabilities.
Author-Email: ilikecubesnstuff <25328250+ilikecubesnstuff@users.noreply.github.com>
License: MIT
Classifier: Intended Audience :: Science/Research
Classifier: License :: OSI Approved :: MIT License
Classifier: Programming Language :: Python :: 3 :: Only
Classifier: Programming Language :: Python :: 3.11
Classifier: Programming Language :: Python :: 3.12
Classifier: Topic :: Scientific/Engineering :: Physics
Requires-Python: >=3.11
Requires-Dist: pidgey>=1.0.4
Requires-Dist: matplotlib>=3.8.2
Requires-Dist: tqdm>=4.66.1
Requires-Dist: h5py>=3.10.0
Requires-Dist: more_itertools>=10.2.0
Requires-Dist: scipy>=1.13.0
Requires-Dist: astropy>=6.1.0
